banditeval/__init__.py
banditeval/bandits.py
banditeval/factorization.py
banditeval-0.1.1.dist-info/LICENSE
banditeval-0.1.1.dist-info/METADATA
banditeval-0.1.1.dist-info/WHEEL
banditeval-0.1.1.dist-info/top_level.txt
banditeval-0.1.1.dist-info/RECORD
